[
  {
    "date": "28 November 2025_2",
    "entries": [
      {
        "title": "Invite Family Members",
        "text": "• Users can now invite family members to join the app.\n • Added functionality to manage invited members.\n"
      }
    ]
  },
  {
    "date": "28 November 2025_1",
    "entries": [
      {
        "title": "Summary Page",
        "text": "• Weekly and Monthly view shows a chart of the itch, rash and mood for a user.\n • Summary is also added to check for common allergens.\n"
      },
      {
        "title": "Compare Meals Page",
        "text": "• User can now compare meals between two members for a specific date."
      },
      {
        "title": "Results Page Update",
        "text": "• Added Compare and Summary Buttons. \n• Users can now edit and delete entries from the Results Page.\n"
      },
      {
        "title": "Backend",
        "text": "• Data read/write into firebase.\n • App Integrity Enforcements\n"
      },
      {
        "title": "Google Authentication",
        "text": "• Users can now login via Google\n"
      }
    ]
  },
  {
    "date": "27 November 2025_1",
    "entries": [
      {
        "title": "Edit/Delete Entry Buttons",
        "text": "• Added Delete Entry button.\n • Added Edit Entry Button.\n"
      }
    ]
  },
  {
    "date": "26 November 2025_2",
    "entries": [
      {
        "title": "Results Page Updates",
        "text": "• Store last user from level of rash page.\n • Update Color of titles.\n • Check last user entry.\n • Clean up data."
      }
    ]
  },
  {
    "date": "26 November 2025_1",
    "entries": [
      {
        "title": "Results Page Updates",
        "text": "• Bug fixes on displayed data.\n • Clean Results Page display.\n • Added symptoms data from reactions page."
      }
    ]
  },
  {
    "date": "24 November 2025_2",
    "entries": [
      {
        "title": "Internal Release",
        "text": "• Adjusted saving values to map with meal type.\n • All cards are being displayed in Results page."
      }
    ]
  },
  {
    "date": "24 November 2025",
    "entries": [
      {
        "title": "Important Updates",
        "text": "• Data has been restructured and all saved data pointed to preference_service. - All Pages.\n • Reactions is showing the correct mapping from the user log. - Results Page 2.\n • Meal Log is correctly saved under type of course (Breakfast, Lunch) - Results Page 3. \n • Meal_Log_Service is completely removed."
      },
      {
        "title": "Issues",
        "text": "• Rash level and Reactions are overwriting data in Breakfast even though entry is under Lunch.\n • Inserting data in medications crashes the app **List dynamic** is not a subtype of **List String**."
      },
      {
  "title": "Meal Log Structure",
  "text": "Example log for 'John Doe' on 2025-11-24```{\n  \"meals\": {\n    \"breakfast\": {\n      \"boughtOrCooked\": \"Cooked\",\n      \"main\": \"Oatmeal\",\n      \"sides\": \"Banana\",\n      \"snacks\": \"None\",\n      \"drinks\": \"Water\",\n      \"ingredients\": [\"Oats\", \"Milk\", \"Honey\"],\n\n      \"reactions\": [\"Head\", \"Arm_L\"],\n      \"symptoms\": [\"Red patches\"],\n      \"hasReaction\": true,\n\n      \"allergies\": [\"Dairy\", \"Gluten\"],\n\n      \"medications\": [\"Hydrocortisone cream\"],\n\n      \"rash\": {\n        \"rashLevel\": 3.0,\n        \"itchLevel\": 2.0,\n        \"moodLevel\": 4.0\n      }\n    },\n\n    \"lunch\": {\n      \"boughtOrCooked\": \"Bought\",\n      \"main\": \"Chicken Rice\",\n      \"sides\": \"\",\n      \"snacks\": \"None\",\n      \"drinks\": \"Tea\",\n      \"ingredients\": [\"Chicken\", \"Rice\", \"Soy Sauce\"],\n\n      \"reactions\": [],\n      \"symptoms\": [],\n      \"hasReaction\": false,\n\n      \"allergies\": [],\n      \"medications\": [],\n      \"rash\": null\n    },\n\n    \"dinner\": {\n      \"boughtOrCooked\": \"Cooked\",\n      \"main\": \"Pasta\",\n      \"sides\": \"Salad\",\n      \"snacks\": \"Cookies\",\n      \"drinks\": \"Juice\",\n      \"ingredients\": [\"Pasta\", \"Tomato\", \"Cheese\"],\n\n      \"reactions\": [\"Neck\"],\n      \"symptoms\": [\"Mild itch\"],\n      \"hasReaction\": true,\n\n      \"allergies\": [\"Dairy\"],\n      \"medications\": [\"Moisturizer\"],\n\n      \"rash\": {\n        \"rashLevel\": 1.0,\n        \"itchLevel\": 1.0,\n        \"moodLevel\": 5.0\n      }\n    }\n  }\n}\n```"
}


    ]
  },
  {
    "date": "19 November 2025",
    "entries": [
      {
        "title": "Updated Reactions Page",
        "text": "• Added body outline widget to select individual body parts.\n • Selected parts is stored in prefs."
      }
    ]
  },
  {
    "date": "18 November 2025",
    "entries": [
      {
        "title": "Unique Entries",
        "text": "• Each meal log entry is now unique to prevent duplicate entries."
      },
      {
        "title": "Create User Page Improvements",
        "text": "• Added list of users into create user page for easier selection.\n• Improved layout and design for better user experience."
      },
      {
        "title": "Added List of Users Page",
        "text": "• Separated list of users into its own page for better organization."
      },
      {
        "title": "Settings Page",
        "text": "• Added Privacy Policy and Terms and Conditions links.\n • Removed list of users from page."
      },
      {
        "title": "Results Page",
        "text": "• Redesigned flow and design of the results page for better usability."
      },
      {
        "title": "Next Button Location",
        "text": "• Adjusted location of the next button for improved navigation."
      },
      {
        "title": "Renamed Files",
        "text": "• Renamed file names for consistency and clarity."
      },
      {
        "title": "Design Updates",
        "text": "• Updated UI elements for better user experience.\n• Improved color scheme and typography."
      }
    ]
    
  },
  {
    "date": "13 November 2025",
    "entries": [
      {
        "title": "Released Internal Testing ver.1.0.0",
        "text": "• Initial testing phase deployed to limited users.\n• Collecting feedback on usability and performance.",
        "image": "./images/Eczemine_Icon.png"
      }
    ]
  },
  {
    "date": "04 November 2025",
    "entries": [
      {
        "title": "Create User",
        "text": "• First time users greeted with create user page.\n • Scrollwheel birthday selection. \n • Gender selection. \n• Entry editable from **Settings Page**."
      },
      {
        "title": "User Selection",
        "text": "• Dropdown selection of existing users.\n • Scrollwheel date selection. \n • Scrollwheel meal selection (Breakfast, Lunch, Dinner). "
      },
      {
        "title": "Meal Selection",
        "text": "• Breakdown of meal (Main, Sides, Snacks). \n • Food Name Entry. \n • Ingredients Entry. \n • Save Function."
      },
      {
        "title": "Bought or Cook",
        "text": "• Bought or Cook options."
      },
      {
        "title": "Settings Page",
        "text": "• Preview list of users. \n • Edit users."
      },
      {
        "title": "Results Page Setup",
        "text": "• Filter users. \n • Display Meal Log. \n • Filter meals."
      }
    ]
  },
  {
    "date": "27 October 2025",
    "entries": [
      {
        "title": "Start Page Setup",
        "text": "• Blockout for the start page.\n • Entry of names."
      }
    ]
  }
]
